gifos/__init__.py
gifos/config/ansi_escape_colors.toml
gifos/config/gifos_settings.toml
gifos/effects/__init__.py
gifos/effects/text_decode_effect.py
gifos/effects/text_scramble_effect.py
gifos/fonts/gohufont-uni-14.pbm
gifos/fonts/gohufont-uni-14.pil
gifos/gifos.py
gifos/utils/__init__.py
gifos/utils/calc_age.py
gifos/utils/calc_github_rank.py
gifos/utils/convert_ansi_escape.py
gifos/utils/fetch_github_stats.py
gifos/utils/load_config.py
gifos/utils/schemas/__init__.py
gifos/utils/schemas/ansi_escape.py
gifos/utils/schemas/github_user_rank.py
gifos/utils/schemas/github_user_stats.py
gifos/utils/schemas/imagebb_image.py
gifos/utils/schemas/user_age.py
gifos/utils/upload_imgbb.py
github_readme_terminal-0.0.3.dist-info/LICENSE
github_readme_terminal-0.0.3.dist-info/METADATA
github_readme_terminal-0.0.3.dist-info/WHEEL
github_readme_terminal-0.0.3.dist-info/RECORD
