Metadata-Version: 2.1
Name: github-readme-terminal
Version: 0.0.3
Summary: ✨ Elevate your GitHub Profile ReadMe with Minimalistic Retro Terminal GIFs 🚀
Home-page: https://github.com/x0rzavi/github-readme-terminal
License: MIT
Author: Avishek Sen
Author-email: x0rzavi@gmail.com
Requires-Python: >=3.9,<4.0
Classifier: License :: OSI Approved :: MIT License
Classifier: Programming Language :: Python :: 3
Classifier: Programming Language :: Python :: 3.9
Classifier: Programming Language :: Python :: 3.10
Classifier: Programming Language :: Python :: 3.11
Classifier: Programming Language :: Python :: 3.12
Requires-Dist: Pillow (>=10.1.0,<11.0.0)
Requires-Dist: icecream (>=2.1.3,<3.0.0)
Requires-Dist: python-dateutil (>=2.8.2,<3.0.0)
Requires-Dist: python-dotenv (>=1.0.0,<2.0.0)
Requires-Dist: requests (>=2.31.0,<3.0.0)
Requires-Dist: tomli (>=2.0.1,<3.0.0)
Project-URL: Bug Tracker, https://github.com/x0rzavi/github-readme-terminal/issues
Project-URL: Repository, https://github.com/x0rzavi/github-readme-terminal
